agents_for_all/__init__.py
agents_for_all/agent.py
agents_for_all/llms/__init__.py
agents_for_all/llms/anthropic.py
agents_for_all/llms/base_model.py
agents_for_all/llms/direct.py
agents_for_all/llms/gemini.py
agents_for_all/llms/openai.py
agents_for_all/tools/__init__.py
agents_for_all/tools/base_tool.py
agents_for_all/tools/data_analysis.py
agents_for_all/tools/email.py
agents_for_all/tools/file.py
agents_for_all/tools/math.py
agents_for_all/tools/python.py
agents_for_all/tools/shell.py
agents_for_all/tools/web_fetcher.py
agents_for_all/tools/web_search.py
agents_for_all-0.1.5.dist-info/METADATA
agents_for_all-0.1.5.dist-info/WHEEL
agents_for_all-0.1.5.dist-info/top_level.txt
agents_for_all-0.1.5.dist-info/RECORD
