Metadata-Version: 2.4
Name: agents-for-all
Version: 0.1.5
Summary: Modular agent framework combining LLMs and Tools
Author-email: Sailesh Dhungana <dhunganasailesh@gmail.com>
License: Apache-2.0
Project-URL: Homepage, https://github.com/dhungana/agents-for-all.git
Project-URL: Repository, https://github.com/dhungana/agents-for-all
Requires-Python: >=3.10
Requires-Dist: anthropic>=0.51.0
Requires-Dist: google-generativeai>=0.8.5
Requires-Dist: openai>=1.77.0
Requires-Dist: requests>=2.32.3
Requires-Dist: sympy>=1.14.0
Requires-Dist: pandas>=2.2.3
Provides-Extra: dev
Requires-Dist: sphinx>=6.2.1; extra == "dev"
Requires-Dist: furo>=2022.12.7; extra == "dev"
Requires-Dist: graphviz>=0.20.1; extra == "dev"
Requires-Dist: pytest>=7.4.0; extra == "dev"
Requires-Dist: pytest-cov>=4.0.0; extra == "dev"
Requires-Dist: pre-commit>=3.3.0; extra == "dev"
Requires-Dist: build>=1.2.2.post1; extra == "dev"
Requires-Dist: twine>=6.1.0; extra == "dev"
